pycapi.cpython-37m-i386-linux-gnu.so
pycapi-0.82.1.dist-info/METADATA
pycapi-0.82.1.dist-info/top_level.txt
pycapi-0.82.1.dist-info/RECORD
pycapi-0.82.1.dist-info/WHEEL
pycapi-0.82.1.dist-info/LICENSE.md
