Metadata-Version: 2.1
Name: pycapi
Version: 0.82.1
Summary: Over 600 fast Python bindings to the CPython C API.
Home-page: https://github.com/brandtbucher/pycapi
Author: Brandt Bucher
Author-email: brandtbucher@gmail.com
License: MIT
Keywords: API C CPython Python
License-File: LICENSE.md
